[
    {
        "id": 1,
        "names": [
            {
                "lang": "fr",
                "name": "Inconnue"
            },
            {
                "lang": "en",
                "name": "Unknown"
            }
        ],
        "category": "UNKNOWN"
    },
    {
        "id": 2,
        "names": [
            {
                "lang": "fr",
                "name": "Chien"
            },
            {
                "lang": "en",
                "name": "Dog"
            }
        ],
        "category": "MAMMAL"
    },
    {
        "id": 3,
        "names": [
            {
                "lang": "fr",
                "name": "Chat"
            },
            {
                "lang": "en",
                "name": "Cat"
            }
        ],
        "category": "MAMMAL"
    },
    {
        "id": 4,
        "names": [
            {
                "lang": "fr",
                "name": "Lapin"
            },
            {
                "lang": "en",
                "name": "Rabbit"
            }
        ],
        "category": "MAMMAL"
    },
    {
        "id": 5,
        "names": [
            {
                "lang": "fr",
                "name": "Cheval"
            },
            {
                "lang": "en",
                "name": "Horse"
            }
        ],
        "category": "MAMMAL"
    },
    {
        "id": 6,
        "names": [
            {
                "lang": "fr",
                "name": "Hamster"
            },
            {
                "lang": "en",
                "name": "Hamster"
            }
        ],
        "category": "MAMMAL"
    },
    {
        "id": 7,
        "names": [
            {
                "lang": "fr",
                "name": "Cochon d'inde"
            },
            {
                "lang": "en",
                "name": "Guinea pig"
            }
        ],
        "category": "MAMMAL"
    },
    {
        "id": 8,
        "names": [
            {
                "lang": "fr",
                "name": "Serpent"
            },
            {
                "lang": "en",
                "name": "Snake"
            }
        ],
        "category": "REPTILE"
    },
    {
        "id": 9,
        "names": [
            {
                "lang": "fr",
                "name": "Lezard"
            },
            {
                "lang": "en",
                "name": "Lizard"
            }
        ],
        "category": "REPTILE"
    },
    {
        "id": 10,
        "names": [
            {
                "lang": "fr",
                "name": ""
            },
            {
                "lang": "en",
                "name": "Turtle"
            }
        ],
        "category": "REPTILE"
    },
    {
        "id": 11,
        "names": [
            {
                "lang": "fr",
                "name": ""
            },
            {
                "lang": "en",
                "name": "Ferret"
            }
        ],
        "category": "MAMMAL"
    }
]
